{"cameraMode":{"drawMode":0,"name":"Shaded","section":"Shading Mode"},"sceneLighting":true,"audioPlay":false,"sceneViewState":{"m_AlwaysRefresh":false,"showFog":true,"showSkybox":true,"showFlares":true,"showImageEffects":true,"showParticleSystems":true,"showVisualEffectGraphs":true,"m_FxEnabled":true},"in2DMode":false,"pivot":{"x":-67.01792907714844,"y":-91.4625473022461,"z":219.8345184326172},"rotation":{"x":0.19164706766605378,"y":-0.1408991664648056,"z":0.028790976852178575,"w":0.9709804654121399},"size":125.26659393310547,"orthographic":false}